abstract_framehub_client/__init__.py
abstract_framehub_client/client.py
abstract_framehub_client/exceptions.py
abstract_framehub_client/proto/__init__.py
abstract_framehub_client/proto/mongo_pb2.py
abstract_framehub_client/proto/mongo_pb2_grpc.py
abstract_framehub_client/wrappers/__init__.py
abstract_framehub_client/wrappers/collection.py
abstract_framehub_client/wrappers/database.py
abstract_framehub_client-0.1.6.dist-info/METADATA
abstract_framehub_client-0.1.6.dist-info/WHEEL
abstract_framehub_client-0.1.6.dist-info/top_level.txt
abstract_framehub_client-0.1.6.dist-info/RECORD
