Metadata-Version: 2.4
Name: abstract-framehub-client
Version: 0.1.6
Summary: Client Python for AbstractFrameHub Server
Home-page: https://gitlab.com/stackngo-client/abstractframehub-client-python
Author: ThéoMottet
Classifier: Programming Language :: Python :: 3
Classifier: License :: OSI Approved :: MIT License
Requires-Python: >=3.7
Requires-Dist: grpcio
Requires-Dist: protobuf
Dynamic: author
Dynamic: classifier
Dynamic: description
Dynamic: description-content-type
Dynamic: home-page
Dynamic: requires-dist
Dynamic: requires-python
Dynamic: summary
